bigquery_frame/__init__.py
bigquery_frame/auth.py
bigquery_frame/bigquery_builder.py
bigquery_frame/cli/__init__.py
bigquery_frame/cli/diff.py
bigquery_frame/column.py
bigquery_frame/conf.py
bigquery_frame/data_diff/__init__.py
bigquery_frame/data_diff/compare_dataframes_impl.py
bigquery_frame/data_diff/diff_format_options.py
bigquery_frame/data_diff/diff_per_col.py
bigquery_frame/data_diff/diff_result.py
bigquery_frame/data_diff/diff_result_analyzer.py
bigquery_frame/data_diff/diff_result_summary.py
bigquery_frame/data_diff/diff_stats.py
bigquery_frame/data_diff/export.py
bigquery_frame/data_diff/package.py
bigquery_frame/data_diff/schema_diff.py
bigquery_frame/data_type_utils.py
bigquery_frame/dataframe.py
bigquery_frame/dataframe_writer.py
bigquery_frame/exceptions.py
bigquery_frame/field_utils.py
bigquery_frame/fp/README.md
bigquery_frame/fp/__init__.py
bigquery_frame/fp/higher_order.py
bigquery_frame/fp/package.py
bigquery_frame/fp/printable_function.py
bigquery_frame/functions.py
bigquery_frame/graph.py
bigquery_frame/graph_impl/__init__.py
bigquery_frame/graph_impl/connected_components.py
bigquery_frame/grouped_data.py
bigquery_frame/has_bigquery_client.py
bigquery_frame/nested.py
bigquery_frame/nested_impl/__init__.py
bigquery_frame/nested_impl/fields.py
bigquery_frame/nested_impl/package.py
bigquery_frame/nested_impl/print_schema.py
bigquery_frame/nested_impl/schema_string.py
bigquery_frame/nested_impl/select_impl.py
bigquery_frame/nested_impl/unnest_all_fields.py
bigquery_frame/nested_impl/unnest_field.py
bigquery_frame/nested_impl/with_fields.py
bigquery_frame/printing.py
bigquery_frame/py.typed
bigquery_frame/special_characters.py
bigquery_frame/temp_names.py
bigquery_frame/transformations.py
bigquery_frame/transformations_impl/__init__.py
bigquery_frame/transformations_impl/analyze.py
bigquery_frame/transformations_impl/analyze_aggs.py
bigquery_frame/transformations_impl/flatten.py
bigquery_frame/transformations_impl/harmonize_dataframes.py
bigquery_frame-0.5.0.dist-info/LICENSE
bigquery_frame-0.5.0.dist-info/METADATA
bigquery_frame-0.5.0.dist-info/WHEEL
bigquery_frame-0.5.0.dist-info/entry_points.txt
bigquery_frame-0.5.0.dist-info/RECORD
