Metadata-Version: 2.1
Name: bigquery-frame
Version: 0.5.0
Summary: A DataFrame API for Google BigQuery
Home-page: https://github.com/FurcyPin/bigquery-frame
License: Apache-2.0
Keywords: BigQuery,DataFrame
Author: FurcyPin
Requires-Python: >=3.9,<3.13
Classifier: License :: OSI Approved :: Apache Software License
Classifier: Programming Language :: Python :: 3
Classifier: Programming Language :: Python :: 3.9
Classifier: Programming Language :: Python :: 3.10
Classifier: Programming Language :: Python :: 3.11
Classifier: Programming Language :: Python :: 3.12
Requires-Dist: data-diff-viewer (==0.3.2)
Requires-Dist: google-cloud-bigquery (>=3.14.1,<4.0.0)
Requires-Dist: google-cloud-bigquery-storage (>=2.24.0,<3.0.0)
Requires-Dist: tabulate (>=0.9.0,<0.10.0)
Requires-Dist: tqdm (>=4.64.0,<5.0.0)
Project-URL: Repository, https://github.com/FurcyPin/bigquery-frame
